notebooks/__init__.py
oilanalytics/__init__.py
oilanalytics/balances/__init__.py
oilanalytics/balances/balance_config.py
oilanalytics/balances/balance_utils.py
oilanalytics/balances/global_oil_balances.py
oilanalytics/balances/key_agency_comparisons.py
oilanalytics/balances/templates/balance_comparisons.html
oilanalytics/balances/templates/base.html
oilanalytics/eia/__init__.py
oilanalytics/eia/eia.py
oilanalytics/eia/monthly_drilling_report.py
oilanalytics/eia/steo.py
oilanalytics/eia/weeklypetreport.py
oilanalytics/eia/templates/base.html
oilanalytics/eia/templates/doe_weekly_crude.html
oilanalytics/eia/templates/doe_weekly_crude_transfers.html
oilanalytics/eia/templates/doe_weekly_distillates.html
oilanalytics/eia/templates/doe_weekly_email.html
oilanalytics/eia/templates/doe_weekly_ethanol.html
oilanalytics/eia/templates/doe_weekly_fuel.html
oilanalytics/eia/templates/doe_weekly_gasoline.html
oilanalytics/eia/templates/doe_weekly_jet.html
oilanalytics/eia/templates/doe_weekly_lpg.html
oilanalytics/eia/templates/doe_weekly_macros.html
oilanalytics/eia/templates/doe_weekly_refineries.html
oilanalytics/eia/templates/doe_weekly_summary.html
oilanalytics/eia/templates/monthly_drilling_report.html
oilanalytics/eia/templates/monthly_drilling_report_email.html
oilanalytics/energyaspects/__init__.py
oilanalytics/energyaspects/china_stats.py
oilanalytics/energyaspects/europe_diesel_balance.py
oilanalytics/energyaspects/fsu_stats.py
oilanalytics/energyaspects/tars.py
oilanalytics/energyaspects/templates/base.html
oilanalytics/energyaspects/templates/china_stats.html
oilanalytics/energyaspects/templates/ea_macros.html
oilanalytics/energyaspects/templates/europe_diesel_balance.html
oilanalytics/energyaspects/templates/fsu_stats.html
oilanalytics/energyaspects/templates/tars_dashboard.html
oilanalytics/euroilstock/__init__.py
oilanalytics/euroilstock/euroilstock.py
oilanalytics/euroilstock/templates/base.html
oilanalytics/euroilstock/templates/euroilstock.html
oilanalytics-0.3.17.dist-info/METADATA
oilanalytics-0.3.17.dist-info/WHEEL
oilanalytics-0.3.17.dist-info/top_level.txt
oilanalytics-0.3.17.dist-info/RECORD
