Metadata-Version: 2.1
Name: oilanalytics
Version: 0.3.17
Summary: Utilities for oil analytics
Home-page: https://github.com/aeorxc/oilanalytics
Author: aeorxc
License: UNKNOWN
Project-URL: Source, https://github.com/aeorxc/oilanalytics
Platform: UNKNOWN
Classifier: Programming Language :: Python :: 3
Classifier: License :: OSI Approved :: MIT License
Classifier: Operating System :: OS Independent
Requires-Python: >=3.8
Requires-Dist: pandas
Requires-Dist: requests
Requires-Dist: commodutil
Requires-Dist: commodplot
Requires-Dist: python-dotenv
Requires-Dist: cachetools
Requires-Dist: beautifulsoup4
Requires-Dist: myeia
